{
  "Mensajes": [
    {
      "Data": {
        "email": "info@estudioyellimo.com.ar",
        "mensaje": "data",
        "Id": "s6lVSd7b_IY3f7SSAAAB",
        "Date": "Friday  12/08/2022"
      }
    },
    {
      "Data": {
        "email": "marianayel@gmail.com",
        "mensaje": "gfsdhfdsghfdgh",
        "Id": "nlJkqgBhT7xXsOD4AAAB",
        "Date": "Saturday  13/08/2022"
      }
    },
    {
      "Data": {
        "email": "info@estudioyellimo.com.ar",
        "mensaje": "124124",
        "Id": "GtJCwFpwG8aHbkIgAAAB",
        "Date": "Saturday  27/08/2022"
      }
    },
    {
      "Data": {
        "email": "info@estudioyellimo.com.ar",
        "mensaje": "124124",
        "Id": "I8xnpxReor8ehx1-AAAB",
        "Date": "Saturday  27/08/2022"
      }
    },
    {
      "Data": {
        "email": "info@estudioyellimo.com.ar",
        "mensaje": "124124",
        "Id": "MIidmwWv-5dUVMsJAAAB",
        "Date": "Saturday  27/08/2022"
      }
    }
  ]
}